setup.py
espresso/__init__.py
espresso/cli.py
espresso/configuration.py
espresso/helpers.py
espresso/stage.py
espresso/storage.py
espresso.egg-info/PKG-INFO
espresso.egg-info/SOURCES.txt
espresso.egg-info/dependency_links.txt
espresso.egg-info/entry_points.txt
espresso.egg-info/requires.txt
espresso.egg-info/top_level.txt