Metadata-Version: 1.1
Name: espresso
Version: 1.0.14
Summary: Manage the configuration of your servers easily.
Home-page: http://github.com/jorgeecardona/espresso
Author: Jorge E. Cardona
Author-email: jorge@cardona.co
License: BSD
Platform: UNKNOWN
Classifier: Development Status :: 3 - Alpha
Classifier: License :: OSI Approved :: BSD License
